polib.py
polib-1.0.8.dist-info/top_level.txt
polib-1.0.8.dist-info/DESCRIPTION.rst
polib-1.0.8.dist-info/metadata.json
polib-1.0.8.dist-info/WHEEL
polib-1.0.8.dist-info/RECORD
polib-1.0.8.dist-info/METADATA
